rate_limiter/__init__.py
rate_limiter/core.py
key_rate_limiter-0.1.1.dist-info/LICENSE
key_rate_limiter-0.1.1.dist-info/METADATA
key_rate_limiter-0.1.1.dist-info/WHEEL
key_rate_limiter-0.1.1.dist-info/top_level.txt
key_rate_limiter-0.1.1.dist-info/RECORD
