Metadata-Version: 2.1
Name: key-rate-limiter
Version: 0.1.1
Summary: A rate limiter library for managing API key usage.
Home-page: https://github.com/sifeiwl/rate_limiter.git
Author: sifei
Author-email: sifei666@qq.com
Classifier: Programming Language :: Python :: 3
Classifier: License :: OSI Approved :: MIT License
Classifier: Operating System :: OS Independent
Requires-Python: >=3.6
License-File: LICENSE
Requires-Dist: redis
